cybotrade-2.0.5.dist-info/METADATA
cybotrade-2.0.5.dist-info/WHEEL
cybotrade-2.0.5.dist-info/licenses/LICENSE
cybotrade/__init__.py
cybotrade/binance/__init__.py
cybotrade/binance/exceptions.py
cybotrade/binance/linear.py
cybotrade/binance/ws.py
cybotrade/bybit/__init__.py
cybotrade/bybit/exceptions.py
cybotrade/bybit/linear.py
cybotrade/bybit/ws.py
cybotrade/cybotrade.cp312-win_amd64.pyd
cybotrade/cybotrade.pyi
cybotrade/encoder.py
cybotrade/event.py
cybotrade/event.pyi
cybotrade/exceptions.py
cybotrade/http.py
cybotrade/http.pyi
cybotrade/io/__init__.py
cybotrade/io/event.py
cybotrade/io/exchange.py
cybotrade/kucoin/__init__.py
cybotrade/kucoin/exceptions.py
cybotrade/kucoin/linear.py
cybotrade/kucoin/ws.py
cybotrade/logging.py
cybotrade/models.py
cybotrade/py.typed
cybotrade/strategy.py
cybotrade/triggers.py
cybotrade/utils.py
cybotrade-2.0.5.dist-info/RECORD
